<root>
	<styles>
		<include src="s2r://panorama/styles/dotastyles.vcss_c" />
		<include src="s2r://panorama/layout/custom_game/spell_shop/spell_shop.css" />
	</styles>
	 <scripts>
        <include src="s2r://panorama/layout/custom_game/scripts/util.js" />
		<include src="s2r://panorama/layout/custom_game/spell_shop/spell_shop.js" />
	</scripts>  
	<Panel style="width:100%;height:100%;" hittest="false">
        <Panel class="SpellMapPanel" id="SpellMapPanel">
            <Panel class="SpellButtonOpen" id="SpellButtonOpen" onactivate="SpellShop_OpenSpellShop();">
                <Panel class="SpellButtonOpenIcon" />
            </Panel>
            <Panel class="SpellButtonOpenTroll" id="SpellButtonOpenTroll" onactivate="SpellShop_OpenSpellShoTroll();">
                <Panel class="SpellButtonOpenIconTroll" />
            </Panel>
            <Panel class="ActivatedSpell" id="ActivatedSpell1">
                <Panel class="ActivatedSpellIcon" id="ActivatedSpellIcon1" />
            </Panel>
            <Panel class="ActivatedSpell" id="ActivatedSpell2">
                <Panel class="ActivatedSpellIcon" id="ActivatedSpellIcon2" />
            </Panel>
            <Panel class="ActivatedSpell" id="ActivatedSpell3">
                <Panel class="ActivatedSpellIcon" id="ActivatedSpellIcon3" />
            </Panel>
        </Panel>
        <Panel class="SpellShopPanel CloseSpellShop" id="SpellShopPanel">
            <Panel class="CloseSpellShopButton" onactivate="SpellShop_CloseSpellShop();"/>
            <Panel class="SpellShopPanelBody">
                <Panel class="SpellShopSpellsList">
                    <Label class="SpellShopSpellsListChoose" text="#SpellShop_ChooseSpell"/>
                    <Panel class="SpellShopSpellsListBody" id="SpellShopSpellsListBody" />
                    <!-- remove buy random aspect
                    <Panel class="SpellShopPanelBuy">
                        <Label class="UnlockPanelBuyButtonDescription" text="#SpellShop_DescriptionBuy" />
                        <Panel class="UnlockPanelBuy">
                            <Panel class="UnlockPanelBuyButton" id="UnlockPanelBuyButton" onactivate="SpellShop_BuyRandomSpell();">
                                <Label text="#SpellShop_Buy"/>
                            </Panel>
                            <Panel class="UnlockPanelBuyButtonCost">
                                <Panel class="UnlockPanelBuyButtonCostIcon" />
                                <Label class="UnlockPanelBuyButtonCostLabel" id="UnlockPanelBuyButtonCostLabel" text="0" />
                            </Panel>
                        </Panel>
                    </Panel>
                    -->
                </Panel>
                <Panel class="PreviewSpellInfo" id="PreviewSpellInfo" />
            </Panel>
        </Panel>
	</Panel>
</root>
